xontrib/openai.py
xontrib_openai-0.1.0.dist-info/LICENSE
xontrib_openai-0.1.0.dist-info/METADATA
xontrib_openai-0.1.0.dist-info/WHEEL
xontrib_openai-0.1.0.dist-info/RECORD
