Metadata-Version: 2.1
Name: xontrib-openai
Version: 0.1.0
Summary: Use Open AI models in xonsh shell.
Home-page: https://github.com/anki-code/xontrib-openai
License: MIT
Keywords: xontrib,xonsh
Author: anki-code
Author-email: a@a.a
Requires-Python: >=3.8
Classifier: Intended Audience :: Developers
Classifier: License :: OSI Approved :: MIT License
Classifier: Natural Language :: English
Classifier: Operating System :: OS Independent
Classifier: Programming Language :: Python :: 3
Classifier: Programming Language :: Python :: 3.8
Classifier: Programming Language :: Python :: 3.9
Classifier: Programming Language :: Python :: 3.10
Classifier: Programming Language :: Python :: 3.11
Classifier: Programming Language :: Python :: 3
Classifier: Topic :: System :: Shells
Classifier: Topic :: System :: System Shells
Classifier: Topic :: Terminals
Requires-Dist: openai (>=0.27)
Requires-Dist: xonsh (>=0.12.5)
Project-URL: Code, https://github.com/anki-code/xontrib-openai
Project-URL: Documentation, https://github.com/anki-code/xontrib-openai/blob/master/README.md
Project-URL: Issue tracker, https://github.com/anki-code/xontrib-openai/issues
Project-URL: Repository, https://github.com/anki-code/xontrib-openai
